{
  "$schema": "data/seeds/bootstrap.json — contenu de référence du programme",
  "description": "Lieux, personnes et récits originaux. Injectés via 'node scripts/seed-bootstrap.js' lors du déploiement initial. Le contenu utilisateur (data/*.json) n'est pas dans git.",
  "places": [
    {
      "id": "saint-roman-de-codieres",
      "primaryName": "Saint-Roman-de-Codières",
      "lat": 44.0027,
      "lng": 3.7786,
      "description": "Village du piémont cévenol, en Gard, dans la vallée de la Crenze entre Sumène et Le Vigan. Point de départ du projet Mémoire des Cévennes : on commence ici, on s'élargira aux vallées voisines ensuite.",
      "aliases": [
        {
          "name": "Sant Roman de Codièras",
          "context": "occitan"
        },
        {
          "name": "Saint-Roman",
          "context": "usuel"
        },
        {
          "name": "Codières",
          "context": "ancien"
        }
      ],
      "status": "approved",
      "createdAt": "2026-04-23T00:00:00.000Z",
      "submittedAt": "2026-04-23T00:00:00.000Z",
      "reviewedAt": "2026-04-23T00:00:00.000Z",
      "reviewedBy": "bootstrap",
      "visibility": "members"
    },
    {
      "id": "les-combes",
      "primaryName": "Les Combes",
      "lat": 44.004,
      "lng": 3.775,
      "description": "Hameau contigu à Saint-Roman-de-Codières, sur la même rive de la Crenze. Point de repère historique : la place de la mairie y est située.",
      "aliases": [],
      "status": "approved",
      "createdAt": "2026-04-24T00:00:00.000Z",
      "submittedAt": "2026-04-24T00:00:00.000Z",
      "reviewedAt": "2026-04-24T00:00:00.000Z",
      "reviewedBy": "bootstrap",
      "visibility": "members"
    },
    {
      "id": "mas-de-la-coste",
      "primaryName": "Mas de la Coste",
      "lat": 44.01,
      "lng": 3.775,
      "description": "Exemple fictif pour illustrer le projet : un mas cévenol sur un versant exposé au midi, sur la crête au-dessus de Saint-Roman-de-Codières. Aliases multiples dans le temps et selon les personnes.",
      "aliases": [
        {
          "name": "La Ferme Vieille",
          "context": "cadastre",
          "startYear": 1812,
          "endYear": 1920
        },
        {
          "name": "Lo Mas de la Còsta",
          "context": "occitan"
        },
        {
          "name": "Chez Suzette",
          "context": "familial",
          "usedBy": "pierre-duval",
          "startYear": 1970
        },
        {
          "name": "Le mazet là-haut",
          "context": "oral local"
        }
      ],
      "status": "approved",
      "createdAt": "2026-04-23T00:00:00.000Z",
      "submittedAt": "2026-04-23T00:00:00.000Z",
      "reviewedAt": "2026-04-23T00:00:00.000Z",
      "reviewedBy": "bootstrap",
      "visibility": "members"
    },
    {
      "id": "mont-aigoual",
      "primaryName": "Mont Aigoual",
      "lat": 44.1214,
      "lng": 3.5814,
      "description": "Sommet emblématique des Cévennes, à 1565 m. Observatoire météorologique historique, et théâtre du plus grand reboisement volontaire de France à la fin du XIXe siècle. Plus au nord de Saint-Roman — visible par beau temps depuis la crête de la Fage.",
      "aliases": [
        {
          "name": "L'Aigoual",
          "context": "local"
        },
        {
          "name": "L'Agoal",
          "context": "occitan"
        }
      ],
      "status": "approved",
      "createdAt": "2026-04-23T00:00:00.000Z",
      "submittedAt": "2026-04-23T00:00:00.000Z",
      "reviewedAt": "2026-04-23T00:00:00.000Z",
      "reviewedBy": "bootstrap",
      "visibility": "members"
    }
  ],
  "people": [
    {
      "id": "georges-fabre",
      "primaryName": "Georges Fabre",
      "gender": "M",
      "aliases": [
        {
          "name": "Le reboiseur de l'Aigoual",
          "context": "historique"
        }
      ],
      "birth": {
        "year": 1844,
        "month": 10,
        "day": 25
      },
      "death": {
        "year": 1911,
        "month": 11,
        "day": 20
      },
      "bio": "Conservateur des Eaux et Forêts, instigateur du reboisement du massif de l'Aigoual à partir de 1875. On lui doit la hêtraie de l'Aigoual et l'observatoire météorologique au sommet.",
      "parents": [],
      "spouses": [],
      "status": "approved",
      "createdAt": "2026-04-23T00:00:00.000Z",
      "submittedAt": "2026-04-23T00:00:00.000Z",
      "reviewedAt": "2026-04-23T00:00:00.000Z",
      "reviewedBy": "bootstrap",
      "visibility": "members"
    },
    {
      "id": "ernest-boissier",
      "primaryName": "Ernest Boissier",
      "gender": "M",
      "aliases": [],
      "birth": {
        "year": 1880
      },
      "death": {
        "year": 1955
      },
      "bio": "Exemple fictif — grand-père paternel de Suzanne.",
      "parents": [],
      "spouses": [
        {
          "id": "anne-rieu",
          "start": 1904,
          "kind": "mariage"
        }
      ],
      "status": "approved",
      "createdAt": "2026-04-23T00:00:00.000Z",
      "submittedAt": "2026-04-23T00:00:00.000Z",
      "reviewedAt": "2026-04-23T00:00:00.000Z",
      "reviewedBy": "bootstrap",
      "visibility": "members"
    },
    {
      "id": "anne-rieu",
      "primaryName": "Anne Boissier",
      "maidenName": "Rieu",
      "gender": "F",
      "aliases": [],
      "birth": {
        "year": 1882
      },
      "death": {
        "year": 1960
      },
      "bio": "Exemple fictif — grand-mère paternelle de Suzanne.",
      "parents": [],
      "spouses": [
        {
          "id": "ernest-boissier",
          "start": 1904,
          "kind": "mariage"
        }
      ],
      "status": "approved",
      "createdAt": "2026-04-23T00:00:00.000Z",
      "submittedAt": "2026-04-23T00:00:00.000Z",
      "reviewedAt": "2026-04-23T00:00:00.000Z",
      "reviewedBy": "bootstrap",
      "visibility": "members"
    },
    {
      "id": "jean-roumieux",
      "primaryName": "Jean Roumieux",
      "gender": "M",
      "aliases": [],
      "birth": {
        "year": 1875
      },
      "death": {
        "year": 1942
      },
      "bio": "Exemple fictif — grand-père maternel de Suzanne.",
      "parents": [],
      "spouses": [
        {
          "id": "jeanne-agulhon",
          "start": 1903,
          "kind": "mariage"
        }
      ],
      "status": "approved",
      "createdAt": "2026-04-23T00:00:00.000Z",
      "submittedAt": "2026-04-23T00:00:00.000Z",
      "reviewedAt": "2026-04-23T00:00:00.000Z",
      "reviewedBy": "bootstrap",
      "visibility": "members"
    },
    {
      "id": "jeanne-agulhon",
      "primaryName": "Jeanne Roumieux",
      "maidenName": "Agulhon",
      "gender": "F",
      "aliases": [],
      "birth": {
        "year": 1880
      },
      "death": {
        "year": 1965
      },
      "bio": "Exemple fictif — grand-mère maternelle de Suzanne.",
      "parents": [],
      "spouses": [
        {
          "id": "jean-roumieux",
          "start": 1903,
          "kind": "mariage"
        }
      ],
      "status": "approved",
      "createdAt": "2026-04-23T00:00:00.000Z",
      "submittedAt": "2026-04-23T00:00:00.000Z",
      "reviewedAt": "2026-04-23T00:00:00.000Z",
      "reviewedBy": "bootstrap",
      "visibility": "members"
    },
    {
      "id": "paul-boissier",
      "primaryName": "Paul Boissier",
      "gender": "M",
      "aliases": [
        {
          "name": "Paulin",
          "context": "familial"
        }
      ],
      "birth": {
        "year": 1905
      },
      "death": {
        "year": 1978
      },
      "bio": "Exemple fictif — père de Suzanne. Paysan au Mas de la Coste, muletier occasionnel vers Alès.",
      "parents": [
        {
          "id": "ernest-boissier",
          "kind": "bio"
        },
        {
          "id": "anne-rieu",
          "kind": "bio"
        }
      ],
      "spouses": [
        {
          "id": "celeste-roumieux",
          "start": 1928,
          "kind": "mariage"
        }
      ],
      "status": "approved",
      "createdAt": "2026-04-23T00:00:00.000Z",
      "submittedAt": "2026-04-23T00:00:00.000Z",
      "reviewedAt": "2026-04-23T00:00:00.000Z",
      "reviewedBy": "bootstrap",
      "visibility": "members"
    },
    {
      "id": "celeste-roumieux",
      "primaryName": "Céleste Boissier",
      "maidenName": "Roumieux",
      "gender": "F",
      "aliases": [],
      "birth": {
        "year": 1908
      },
      "death": {
        "year": 1985
      },
      "bio": "Exemple fictif — mère de Suzanne. Tisserande de châtaigniers, connue pour ses recettes de châtaignes rôties.",
      "parents": [
        {
          "id": "jean-roumieux",
          "kind": "bio"
        },
        {
          "id": "jeanne-agulhon",
          "kind": "bio"
        }
      ],
      "spouses": [
        {
          "id": "paul-boissier",
          "start": 1928,
          "kind": "mariage"
        }
      ],
      "status": "approved",
      "createdAt": "2026-04-23T00:00:00.000Z",
      "submittedAt": "2026-04-23T00:00:00.000Z",
      "reviewedAt": "2026-04-23T00:00:00.000Z",
      "reviewedBy": "bootstrap",
      "visibility": "members"
    },
    {
      "id": "joseph-boissier",
      "primaryName": "Joseph Boissier",
      "gender": "M",
      "aliases": [
        {
          "name": "Jo",
          "context": "familial"
        }
      ],
      "birth": {
        "year": 1929
      },
      "death": {
        "year": 2012
      },
      "bio": "Exemple fictif — frère aîné de Suzanne. Maquisard pendant la guerre, puis forestier sur l'Aigoual.",
      "parents": [
        {
          "id": "paul-boissier",
          "kind": "bio"
        },
        {
          "id": "celeste-roumieux",
          "kind": "bio"
        }
      ],
      "spouses": [],
      "status": "approved",
      "createdAt": "2026-04-23T00:00:00.000Z",
      "submittedAt": "2026-04-23T00:00:00.000Z",
      "reviewedAt": "2026-04-23T00:00:00.000Z",
      "reviewedBy": "bootstrap",
      "visibility": "members"
    },
    {
      "id": "suzanne-duval",
      "primaryName": "Suzanne Duval",
      "maidenName": "Boissier",
      "gender": "F",
      "aliases": [
        {
          "name": "Suzette",
          "context": "familial"
        },
        {
          "name": "la petite Duval",
          "context": "village"
        }
      ],
      "birth": {
        "year": 1932,
        "month": 3,
        "placeId": "mas-de-la-coste"
      },
      "death": {
        "year": 2019
      },
      "bio": "Exemple fictif — figure du Mas de la Coste. Dernière habitante née au mas, gardienne des récits de la famille Boissier-Duval.",
      "parents": [
        {
          "id": "paul-boissier",
          "kind": "bio"
        },
        {
          "id": "celeste-roumieux",
          "kind": "bio"
        }
      ],
      "spouses": [
        {
          "id": "henri-duval",
          "start": 1952,
          "end": 2001,
          "kind": "mariage"
        }
      ],
      "status": "approved",
      "createdAt": "2026-04-23T00:00:00.000Z",
      "submittedAt": "2026-04-23T00:00:00.000Z",
      "reviewedAt": "2026-04-23T00:00:00.000Z",
      "reviewedBy": "bootstrap",
      "visibility": "members"
    },
    {
      "id": "henri-duval",
      "primaryName": "Henri Duval",
      "gender": "M",
      "aliases": [],
      "birth": {
        "year": 1930
      },
      "death": {
        "year": 2001
      },
      "bio": "Exemple fictif — mari de Suzanne. Cheminot à la Grand-Combe puis retraité au Mas de la Coste.",
      "parents": [],
      "spouses": [
        {
          "id": "suzanne-duval",
          "start": 1952,
          "end": 2001,
          "kind": "mariage"
        }
      ],
      "status": "approved",
      "createdAt": "2026-04-23T00:00:00.000Z",
      "submittedAt": "2026-04-23T00:00:00.000Z",
      "reviewedAt": "2026-04-23T00:00:00.000Z",
      "reviewedBy": "bootstrap",
      "visibility": "members"
    },
    {
      "id": "pierre-duval",
      "primaryName": "Pierre Duval",
      "gender": "M",
      "aliases": [],
      "birth": {
        "year": 1954
      },
      "bio": "Exemple fictif — fils aîné de Suzanne et Henri. Contributeur fréquent des récits de la famille.",
      "parents": [
        {
          "id": "suzanne-duval",
          "kind": "bio"
        },
        {
          "id": "henri-duval",
          "kind": "bio"
        }
      ],
      "spouses": [],
      "status": "approved",
      "createdAt": "2026-04-23T00:00:00.000Z",
      "submittedAt": "2026-04-23T00:00:00.000Z",
      "reviewedAt": "2026-04-23T00:00:00.000Z",
      "reviewedBy": "bootstrap",
      "visibility": "members"
    },
    {
      "id": "marie-duval",
      "primaryName": "Marie Duval",
      "gender": "F",
      "aliases": [],
      "birth": {
        "year": 1957
      },
      "bio": "Exemple fictif — fille de Suzanne et Henri. Partie à Montpellier mais revient au mas à chaque été.",
      "parents": [
        {
          "id": "suzanne-duval",
          "kind": "bio"
        },
        {
          "id": "henri-duval",
          "kind": "bio"
        }
      ],
      "spouses": [],
      "status": "approved",
      "createdAt": "2026-04-23T00:00:00.000Z",
      "submittedAt": "2026-04-23T00:00:00.000Z",
      "reviewedAt": "2026-04-23T00:00:00.000Z",
      "reviewedBy": "bootstrap",
      "visibility": "members"
    }
  ],
  "stories": [
    {
      "id": "saint-roman-magnanaries",
      "placeId": "saint-roman-de-codieres",
      "type": "text",
      "title": "Les magnanaries et le chemin de la soie",
      "body": "Au XIXe siècle, Saint-Roman-de-Codières comptait plusieurs magnanaries où les foyers élevaient des vers à soie pour la filature de Ganges. Chaque printemps, les mûriers bordaient les chemins menant au village.",
      "memoryDate": "XIXe siècle",
      "mentions": [
        {
          "start": 16,
          "end": 39,
          "type": "place",
          "entityId": "saint-roman-de-codieres"
        }
      ],
      "mediaFiles": [],
      "status": "approved",
      "createdAt": "2026-04-23T00:00:00.000Z",
      "submittedAt": "2026-04-23T00:00:00.000Z",
      "reviewedAt": "2026-04-23T00:00:00.000Z",
      "reviewedBy": "bootstrap",
      "visibility": "members"
    },
    {
      "id": "reboisement-aigoual",
      "placeId": "mont-aigoual",
      "type": "text",
      "title": "Le reboisement de l'Aigoual",
      "body": "Georges Fabre, conservateur des Eaux et Forêts, entreprit à partir de 1875 le reboisement du mont Aigoual. En quarante ans, il y plantera plus de 6 000 hectares, transformant un massif dévasté en l'une des plus grandes hêtraies de France.",
      "memoryDate": "1875-1915",
      "mentions": [
        {
          "start": 0,
          "end": 13,
          "type": "person",
          "entityId": "georges-fabre"
        },
        {
          "start": 93,
          "end": 105,
          "type": "place",
          "entityId": "mont-aigoual"
        }
      ],
      "mediaFiles": [],
      "status": "approved",
      "createdAt": "2026-04-23T00:00:00.000Z",
      "submittedAt": "2026-04-23T00:00:00.000Z",
      "reviewedAt": "2026-04-23T00:00:00.000Z",
      "reviewedBy": "bootstrap",
      "visibility": "members"
    },
    {
      "id": "chataignes-maquis",
      "placeId": "mas-de-la-coste",
      "type": "text",
      "title": "Les châtaignes du maquis",
      "body": "Suzette nous racontait qu'au Mas de la Coste, pendant la guerre, son frère Joseph Boissier était parti au maquis, et que sa mère Céleste faisait griller les châtaignes toutes les nuits pour le ravitaillement.",
      "memoryDate": "1943-1944",
      "contributorId": "pierre-duval",
      "mentions": [
        {
          "start": 0,
          "end": 7,
          "type": "person",
          "entityId": "suzanne-duval"
        },
        {
          "start": 29,
          "end": 44,
          "type": "place",
          "entityId": "mas-de-la-coste"
        },
        {
          "start": 75,
          "end": 90,
          "type": "person",
          "entityId": "joseph-boissier"
        },
        {
          "start": 129,
          "end": 136,
          "type": "person",
          "entityId": "celeste-roumieux"
        }
      ],
      "mediaFiles": [],
      "completions": [
        {
          "id": "exemple-comp-1",
          "body": "Ma grand-mère Céleste me disait que le plus difficile, c'était d'allumer le feu sans fumée — sinon on voyait le panache depuis la crête et les Allemands savaient qu'une ferme était habitée. Elle mettait toujours des feuilles vertes humides au-dessus pour étouffer la flamme.",
          "createdAt": "2026-04-24T00:00:00.000Z",
          "submittedAt": "2026-04-24T00:00:00.000Z",
          "reviewedAt": "2026-04-24T00:00:00.000Z",
          "reviewedBy": "bootstrap",
          "status": "approved",
          "submittedBy": {
            "name": "Marie Duval",
            "writtenFrom": "Montpellier",
            "relationship": "petite-fille de Suzanne"
          }
        }
      ],
      "status": "approved",
      "createdAt": "2026-04-23T00:00:00.000Z",
      "submittedAt": "2026-04-23T00:00:00.000Z",
      "reviewedAt": "2026-04-23T00:00:00.000Z",
      "reviewedBy": "bootstrap",
      "visibility": "members"
    }
  ]
}
